{
  "experiment_name": "rag_usdc_faiss_mock_debug",
  "condition": "rag",
  "models": {
    "test_agent": {
      "backend": "mock",
      "model_name": "mock"
    },
    "adversary_agent": {
      "backend": "mock",
      "model_name": "mock"
    },
    "judge": {
      "backend": "mock",
      "model_name": "mock"
    }
  },
  "retrieval": {
    "backend": "faiss",
    "index_path": "data/rag_indexes/usdc_selected.faiss",
    "metadata_path": "data/rag_indexes/usdc_selected_metadata.json",
    "embedding_model": "sentence-transformers/all-MiniLM-L6-v2",
    "top_k": 3,
    "search_k": 100
  },
  "rounds": 1,
  "seeds": [42],
  "topics": [
    {
      "name": "climate_change",
      "question": "Should governments take stronger action against climate change?"
    }
  ],
  "stance_pairs": [
    {
      "test_agent_stance": "pro",
      "test_agent_stance_score": 2,
      "adversary_stance": "contra",
      "adversary_stance_score": -2
    },
    {
      "test_agent_stance": "contra",
      "test_agent_stance_score": -2,
      "adversary_stance": "pro",
      "adversary_stance_score": 2
    }
  ],
  "output_dir": "outputs/transcripts"
}